Simple_PairsTrading/Simple_PairsTrading.py
Simple_PairsTrading/__init__.py
Simple_PairsTrading-1.0.1.dist-info/LICENSE.txt
Simple_PairsTrading-1.0.1.dist-info/METADATA
Simple_PairsTrading-1.0.1.dist-info/WHEEL
Simple_PairsTrading-1.0.1.dist-info/top_level.txt
Simple_PairsTrading-1.0.1.dist-info/RECORD
