Metadata-Version: 2.1
Name: Simple-PairsTrading
Version: 1.0.1
Summary: Find ideal candidates
Home-page: https://github.com/HindyDS/Pairs-Trading
Author: Hindy Yuen
Author-email: hindy888@hotmail.com
License: MIT
Keywords: Pairs Trading
Platform: UNKNOWN
Classifier: Development Status :: 5 - Production/Stable
Classifier: Intended Audience :: Developers
Classifier: Topic :: Software Development :: Build Tools
Classifier: License :: OSI Approved :: MIT License
Classifier: Programming Language :: Python :: 3.7
Classifier: Programming Language :: Python :: 3.8
Classifier: Programming Language :: Python :: 3.9
Requires-Python: >=3.6
